sec_eagle/__init__.py
sec_eagle/main.py
sec_eagle-0.1.300.dist-info/METADATA
sec_eagle-0.1.300.dist-info/WHEEL
sec_eagle-0.1.300.dist-info/top_level.txt
sec_eagle-0.1.300.dist-info/RECORD
