Metadata-Version: 2.4
Name: sec_eagle
Version: 0.1.300
Summary: A Python package for parsing SEC data
Author: Bryce Gerber
Classifier: Programming Language :: Python :: 3
Classifier: Operating System :: OS Independent
Requires-Python: >=3.6
Requires-Dist: requests
Requires-Dist: pandas
Requires-Dist: beautifulsoup4
Requires-Dist: numpy
Requires-Dist: lxml
Dynamic: author
Dynamic: classifier
Dynamic: description
Dynamic: description-content-type
Dynamic: requires-dist
Dynamic: requires-python
Dynamic: summary
